[{"name":"Tachiyomi: MangaDex","pkg":"eu.kanade.tachiyomi.extension.all.mangadex","apk":"tachiyomi-all.mangadex-v1.4.211.apk","lang":"all","code":211,"version":"1.4.211","nsfw":0,"sources":[{"name":"MangaDex","lang":"af","id":"4638673959522768501","baseUrl":"https://mangadex.org"},{"name":"MangaDex","lang":"sq","id":"987803387023224960","baseUrl":"https://mangadex.org"},{"name":"MangaDex","lang":"ar","id":"3339599426223341161","baseUrl":"https://mangadex.org"},{"name":"MangaDex","lang":"az","id":"9127464796236242233","baseUrl":"https://mangadex.org"},{"name":"MangaDex","lang":"eu","id":"1553736397938752611","baseUrl":"https://mangadex.org"},{"name":"MangaDex","lang":"be","id":"3601180820582582605","baseUrl":"https://mangadex.org"},{"name":"MangaDex","lang":"bn","id":"4150470519566206911","baseUrl":"https://mangadex.org"},{"name":"MangaDex","lang":"bg","id":"5463447640980279236","baseUrl":"https://mangadex.org"},{"name":"MangaDex","lang":"my","id":"1347402746269051958","baseUrl":"https://mangadex.org"},{"name":"MangaDex","lang":"ca","id":"5860541308324630662","baseUrl":"https://mangadex.org"},{"name":"MangaDex","lang":"zh-Hans","id":"5148895169070562838","baseUrl":"https://mangadex.org"},{"name":"MangaDex","lang":"zh-Hant","id":"1493666528525752601","baseUrl":"https://mangadex.org"},{"name":"MangaDex","lang":"cv","id":"2072928884077964642","baseUrl":"https://mangadex.org"},{"name":"MangaDex","lang":"hr","id":"8548374501079910130","baseUrl":"https://mangadex.org"},{"name":"MangaDex","lang":"cs","id":"3578612018159256808","baseUrl":"https://mangadex.org"},{"name":"MangaDex","lang":"da","id":"425785191804166217","baseUrl":"https://mangadex.org"},{"name":"MangaDex","lang":"nl","id":"6750440049024086587","baseUrl":"https://mangadex.org"},{"name":"MangaDex","lang":"en","id":"2499283573021220255","baseUrl":"https://mangadex.org"},{"name":"MangaDex","lang":"eo","id":"2819252027406613931","baseUrl":"https://mangadex.org"},{"name":"MangaDex","lang":"et","id":"8773024089257004344","baseUrl":"https://mangadex.org"},{"name":"MangaDex","lang":"fil","id":"8578871918181236609","baseUrl":"https://mangadex.org"},{"name":"MangaDex","lang":"fi","id":"8254121249433835847","baseUrl":"https://mangadex.org"},{"name":"MangaDex","lang":"fr","id":"4505830566611664829","baseUrl":"https://mangadex.org"},{"name":"MangaDex","lang":"ka","id":"8952567078513962586","baseUrl":"https://mangadex.org"},{"name":"MangaDex","lang":"de","id":"5098537545549490547","baseUrl":"https://mangadex.org"},{"name":"MangaDex","lang":"el","id":"3260701926561129943","baseUrl":"https://mangadex.org"},{"name":"MangaDex","lang":"he","id":"1424273154577029558","baseUrl":"https://mangadex.org"},{"name":"MangaDex","lang":"hi","id":"6840513937945146538","baseUrl":"https://mangadex.org"},{"name":"MangaDex","lang":"hu","id":"4284949320785450865","baseUrl":"https://mangadex.org"},{"name":"MangaDex","lang":"ga","id":"3686775439235747344","baseUrl":"https://mangadex.org"},{"name":"MangaDex","lang":"id","id":"3807502156582598786","baseUrl":"https://mangadex.org"},{"name":"MangaDex","lang":"it","id":"1952071260038453057","baseUrl":"https://mangadex.org"},{"name":"MangaDex","lang":"ja","id":"1411768577036936240","baseUrl":"https://mangadex.org"},{"name":"MangaDex","lang":"jv","id":"1573550798452063564","baseUrl":"https://mangadex.org"},{"name":"MangaDex","lang":"kk","id":"8884149958776527952","baseUrl":"https://mangadex.org"},{"name":"MangaDex","lang":"ko","id":"3285208643537017688","baseUrl":"https://mangadex.org"},{"name":"MangaDex","lang":"la","id":"764587568075398530","baseUrl":"https://mangadex.org"},{"name":"MangaDex","lang":"lt","id":"737986167355114438","baseUrl":"https://mangadex.org"},{"name":"MangaDex","lang":"ms","id":"1471784905273036181","baseUrl":"https://mangadex.org"},{"name":"MangaDex","lang":"mn","id":"5967745367608513818","baseUrl":"https://mangadex.org"},{"name":"MangaDex","lang":"ne","id":"954368055061084457","baseUrl":"https://mangadex.org"},{"name":"MangaDex","lang":"no","id":"4872213291993424667","baseUrl":"https://mangadex.org"},{"name":"MangaDex","lang":"fa","id":"3781216447842245147","baseUrl":"https://mangadex.org"},{"name":"MangaDex","lang":"pl","id":"8033579885162383068","baseUrl":"https://mangadex.org"},{"name":"MangaDex","lang":"pt-BR","id":"2655149515337070132","baseUrl":"https://mangadex.org"},{"name":"MangaDex","lang":"pt","id":"5189216366882819742","baseUrl":"https://mangadex.org"},{"name":"MangaDex","lang":"ro","id":"4774459486579224459","baseUrl":"https://mangadex.org"},{"name":"MangaDex","lang":"ru","id":"2098905203823335614","baseUrl":"https://mangadex.org"},{"name":"MangaDex","lang":"sr","id":"3507378005483435886","baseUrl":"https://mangadex.org"},{"name":"MangaDex","lang":"sk","id":"2875503798326600410","baseUrl":"https://mangadex.org"},{"name":"MangaDex","lang":"es-419","id":"4938773340256184018","baseUrl":"https://mangadex.org"},{"name":"MangaDex","lang":"es","id":"6400665728063187402","baseUrl":"https://mangadex.org"},{"name":"MangaDex","lang":"sv","id":"1145824452519314725","baseUrl":"https://mangadex.org"},{"name":"MangaDex","lang":"ta","id":"4273071356706429527","baseUrl":"https://mangadex.org"},{"name":"MangaDex","lang":"te","id":"6886894829142702925","baseUrl":"https://mangadex.org"},{"name":"MangaDex","lang":"th","id":"1713554459881080228","baseUrl":"https://mangadex.org"},{"name":"MangaDex","lang":"tr","id":"3846770256925560569","baseUrl":"https://mangadex.org"},{"name":"MangaDex","lang":"uk","id":"5779037855201976894","baseUrl":"https://mangadex.org"},{"name":"MangaDex","lang":"ur","id":"72800122520214493","baseUrl":"https://mangadex.org"},{"name":"MangaDex","lang":"uz","id":"2838715564514827672","baseUrl":"https://mangadex.org"},{"name":"MangaDex","lang":"vi","id":"9194073792736219759","baseUrl":"https://mangadex.org"}]},{"name":"Tachiyomi: Art Lapsa","pkg":"eu.kanade.tachiyomi.extension.en.artlapsa","apk":"tachiyomi-en.artlapsa-v1.4.26.apk","lang":"en","code":26,"version":"1.4.26","nsfw":0,"sources":[{"name":"Art Lapsa","lang":"en","id":"734404203508686053","baseUrl":"https://artlapsa.com"}]},{"name":"Tachiyomi: Asmodeus Scans","pkg":"eu.kanade.tachiyomi.extension.en.asmotoon","apk":"tachiyomi-en.asmotoon-v1.4.24.apk","lang":"en","code":24,"version":"1.4.24","nsfw":0,"sources":[{"name":"Asmodeus Scans","lang":"en","id":"5258838449396844455","baseUrl":"https://asmotoon.com"}]},{"name":"Tachiyomi: Mangabat","pkg":"eu.kanade.tachiyomi.extension.en.mangabat","apk":"tachiyomi-en.mangabat-v1.6.23.apk","lang":"en","code":23,"version":"1.6.23","nsfw":0,"sources":[{"name":"Mangabat","lang":"en","id":"4215511432986138970","baseUrl":"https://www.mangabats.com"}]},{"name":"Tachiyomi: Mangakakalot","pkg":"eu.kanade.tachiyomi.extension.en.mangakakalot","apk":"tachiyomi-en.mangakakalot-v1.6.24.apk","lang":"en","code":24,"version":"1.6.24","nsfw":0,"sources":[{"name":"Mangakakalot","lang":"en","id":"2528986671771677900","baseUrl":"https://www.mangakakalot.gg"}]},{"name":"Tachiyomi: Manganato","pkg":"eu.kanade.tachiyomi.extension.en.manganelo","apk":"tachiyomi-en.manganelo-v1.6.21.apk","lang":"en","code":21,"version":"1.6.21","nsfw":0,"sources":[{"name":"Manganato","lang":"en","id":"1024627298672457456","baseUrl":"https://www.natomanga.com"}]},{"name":"Tachiyomi: RitharScans","pkg":"eu.kanade.tachiyomi.extension.en.ritharscans","apk":"tachiyomi-en.ritharscans-v1.4.24.apk","lang":"en","code":24,"version":"1.4.24","nsfw":0,"sources":[{"name":"RitharScans","lang":"en","id":"8220771912098311271","baseUrl":"https://ritharscans.com"}]}]